solrbackups3-0.4.data/scripts/solrbackups3
solrbackup_s3/__init__.py
solrbackup_s3/backup.py
solrbackups3-0.4.dist-info/METADATA
solrbackups3-0.4.dist-info/DESCRIPTION.rst
solrbackups3-0.4.dist-info/top_level.txt
solrbackups3-0.4.dist-info/metadata.json
solrbackups3-0.4.dist-info/RECORD
solrbackups3-0.4.dist-info/WHEEL
