Metadata-Version: 2.0
Name: solrbackups3
Version: 0.4
Summary: S3 backup solution for Solr
Home-page: https://github.com/yegortokmakov/solrbackups3
Author: yegortokmakov
Author-email: yegor@tokmakov.biz
License: MIT
Platform: UNKNOWN
Requires-Dist: solrbackup
